<?xml version='1.0' encoding='UTF-8'?>
<song xmlns="http://openlyrics.info/namespace/2009/song" version="0.8" createdIn="OpenLP 2.4.6" modifiedIn="OpenLP 2.4.6" modifiedDate="2018-06-21T18:17:03">
  <properties>
    <titles>
      <title>HM339 - O Melhor Amigo</title>
      <title>Sei que o melhor amigo é Cristo!</title>
    </titles>
    <copyright>2001-Imprensa Metodista</copyright>
    <authors>
      <author>Dr. João Gomes da Rocha</author>
    </authors>
  </properties>
  <lyrics>
    <verse name="v1">
      <lines>Sei que o melhor amigo é Cristo!<br/>Quando a tempestade assalta a fé,<br/>Pronto estende a sua mão,<br/>Transquiliza o coração;<br/>Sim, o melhor amigo é Cristo!</lines>
    </verse>
    <verse name="c1">
      <lines>Jesus é o melhor amigo!<br/>Jesus é o melhor amigo!<br/>Repreende com dulçor,<br/>E me anima com vigor!<br/>Sim! O melhor amigo é Cristo!</lines>
    </verse>
    <verse name="v2">
      <lines>Fiel amigo tenho em Cristo!<br/>Nele encontro amor, consolo e paz;<br/>Em seu braço esperarei;<br/>Nenhum mal recearei,<br/>Sim! O melhor amigo é Cristo!</lines>
    </verse>
    <verse name="v3">
      <lines>Minha alma segue o vale escuro?<br/>Desce o corpo às águas do Jordão?<br/>Não receio! pois Jesus,<br/>Salvo, à pátria me conduz.<br/>Sim! O melhor amigo é Cristo!</lines>
    </verse>
    <verse name="v4">
      <lines>No paraíso eterno, todos<br/>Os remidos, transformados já,<br/>Este canto de louvor<br/>Sempre entoam ao Senhor:<br/>Sim! O melhor amigo é Cristo!</lines>
    </verse>
  </lyrics>
</song>
