<?xml version='1.0' encoding='UTF-8'?>
<song xmlns="http://openlyrics.info/namespace/2009/song" version="0.8" createdIn="OpenLP 2.0.1" modifiedIn="OpenLP 2.0.1" modifiedDate="2013-11-14T22:05:14">
  <properties>
    <titles>
      <title>HCC 605 Justiça e Paz</title>
      <title>Salmos 72:1-4, 7, 18</title>
    </titles>
    <copyright>Salmos 72:1-4, 7, 18</copyright>
    <verseOrder>v1</verseOrder>
    <authors>
      <author>Leitura bíblica</author>
    </authors>
    <songbooks>
      <songbook name="Hinário Para o Culto Cristão" entry="605"/>
    </songbooks>
  </properties>
  <lyrics>
    <verse name="v1">
      <lines>Ó Deus, dá ao rei os teus juízos, e a tua justiça ao filho do rei.<br/>Julgue ele ao teu povo com justiça e os teus pobres com equidade.<br/>Que os montes tragam paz ao povo, salve os filhos do necessitado, e esmague o opressor.<br/>Nos seus dias floresça a justiça, e haja abundância de paz enquanto durar a lua.<br/>Bendito seja o Senhor Deus (...) o único que faz maravilhas.</lines>
    </verse>
  </lyrics>
</song>
