<?xml version='1.0' encoding='UTF-8'?>
<song xmlns="http://openlyrics.info/namespace/2009/song" version="0.8" createdIn="OpenLP 2.4.6" modifiedIn="OpenLP 2.4.6" modifiedDate="2018-06-19T21:54:33">
  <properties>
    <titles>
      <title>HC007 - Cristo Cura, Sim!</title>
    </titles>
    <copyright>Harpa Cristã</copyright>
    <authors>
      <author>Autor Desconhecido</author>
    </authors>
  </properties>
  <lyrics>
    <verse name="v1">
      <lines>Contra os males deste mundo,<br/>Deus nos vale só;<br/>Não há mal que Deus não cure,<br/>Pois de nós tem dó.</lines>
    </verse>
    <verse name="c1">
      <lines>Cristo cura, sim,<br/>Cristo cura, sim.<br/>Seu amor por nós é imenso;<br/>Ele cura, sim!</lines>
    </verse>
    <verse name="v2">
      <lines>Derramou Seu sangue puro<br/>P'ra remir a mim;<br/>Quando ungido sou de azeite,<br/>Sou curado, enfim!</lines>
    </verse>
    <verse name="v3">
      <lines>Só noss'alma é bem segura,<br/>Oculta em Jesus;<br/>Ele o bálsamo da vida,<br/>Derramou na cruz.</lines>
    </verse>
    <verse name="v4">
      <lines>Glória a Deus! Eterna glória,<br/>Demos-lhe louvor;<br/>Glória, cânticos e hosanas<br/>Dai ao Redentor!</lines>
    </verse>
  </lyrics>
</song>
