<?xml version='1.0' encoding='UTF-8'?>
<song xmlns="http://openlyrics.info/namespace/2009/song" version="0.8" createdIn="OpenLP 2.4.6" modifiedIn="OpenLP 2.4.6" modifiedDate="2018-06-19T21:56:15">
  <properties>
    <titles>
      <title>HC609 - Vitória Deus Dará A Mim</title>
    </titles>
    <copyright>Harpa Cristã</copyright>
    <authors>
      <author>Autor Desconhecido</author>
    </authors>
  </properties>
  <lyrics>
    <verse name="v1">
      <lines>Vitória Deus dará a mim, eu sei,<br/>Vitória Deus dará a mim, eu sei.<br/>Se eu andar em plena luz,<br/>Confiar só em Jesus,<br/>Vitória Deus dará a mim, eu sei.</lines>
    </verse>
  </lyrics>
</song>
