{
    "livro": "Provérbios",
    "capitulo": 25,
    "titulos": {
        "1": "Símiles e lições morais"
    },
    "versiculos": {
        "1": "São também estes provérbios de Salomão, os quais transcreveram os homens de Ezequias, rei de Judá.",
        "2": "A glória de Deus é encobrir as coisas,",
        "3": "Como a altura dos céus e a profundeza da terra,",
        "4": "Tira da prata a escória,",
        "5": "tira o perverso da presença do rei,",
        "6": "Não te glories na presença do rei,",
        "7": "porque melhor é que te digam: Sobe para aqui!,",
        "8": "não te apresses a litigar,",
        "9": "Pleiteia a tua causa diretamente com o teu próximo",
        "10": "para que não te vitupere aquele que te ouvir,",
        "11": "Como maçãs de ouro em salvas de prata,",
        "12": "Como pendentes e joias de ouro puro,",
        "13": "Como o frescor de neve no tempo da ceifa,",
        "14": "Como nuvens e ventos que não trazem chuva,",
        "15": "A longanimidade persuade o príncipe,",
        "16": "Achaste mel? Come apenas o que te basta,",
        "17": "Não sejas frequente na casa do teu próximo,",
        "18": "Maça, espada e flecha aguda é o homem",
        "19": "Como dente quebrado e pé sem firmeza,",
        "20": "Como quem se despe num dia de frio",
        "21": "Se o que te aborrece tiver fome, dá-lhe pão para comer;",
        "22": "porque assim amontoarás brasas vivas sobre a sua cabeça,",
        "23": "O vento norte traz chuva,",
        "24": "Melhor é morar no canto do eirado",
        "25": "Como água fria para o sedento,",
        "26": "Como fonte que foi turvada e manancial corrupto,",
        "27": "Comer muito mel não é bom;",
        "28": "Como cidade derribada, que não tem muros,"
    }
}