{
    "livro": "Provérbios",
    "capitulo": 28,
    "titulos": {},
    "versiculos": {
        "1": "Os ímpios fogem, mesmo quando",
        "2": "Por causa da transgressão",
        "3": "O pobre que oprime os pobres",
        "4": "Os que abandonam a lei",
        "5": "Os maus não entendem",
        "6": "Melhor é o pobre",
        "7": "Quem guarda a lei",
        "8": "Quem aumenta os seus bens",
        "9": "Quem desvia os ouvidos",
        "10": "Quem desvia os retos",
        "11": "O homem rico é sábio",
        "12": "Quando os justos triunfam,",
        "13": "Quem encobre",
        "14": "Feliz é aquele que sempre",
        "15": "Como leão que ruge",
        "16": "O príncipe sem juízo",
        "17": "O assassino carregado de culpa",
        "18": "Quem anda em integridade",
        "19": "O que lavra a sua terra",
        "20": "O homem fiel será",
        "21": "Parcialidade não é bom,",
        "22": "O ganancioso corre",
        "23": "Quem repreende alguém",
        "24": "Quem rouba o seu pai",
        "25": "O cobiçoso provoca discórdias,",
        "26": "Quem confia",
        "27": "Quem dá aos pobres",
        "28": "Quando os maus se levantam,"
    }
}