<?xml version='1.0' encoding='UTF-8'?>
<song xmlns="http://openlyrics.info/namespace/2009/song" version="0.8" createdIn="OpenLP 2.0.1" modifiedIn="OpenLP 2.0.1" modifiedDate="2013-11-14T21:42:53">
  <properties>
    <titles>
      <title>CC 331 Glória no Porvir</title>
    </titles>
    <verseOrder>v1 c1 v2 c1 v3 c1</verseOrder>
    <authors>
      <author>Fanny Crosby</author>
      <author>Charles Gabriel</author>
    </authors>
    <songbooks>
      <songbook name="Cantor Cristão" entry="331"/>
    </songbooks>
  </properties>
  <lyrics>
    <verse name="v1">
      <lines break="optional">Temos sombras neste vale,<br/>em que estamos a passar;<br/>mas das águas cristalinas<br/>já se vê o marulhar.</lines>
      <lines>Eis que o bom Pastor segreda,<br/>ajudando a prosseguir:<br/>Há, sim, sombras neste vale,<br/>mas há glória no porvir.</lines>
    </verse>
    <verse name="c1">
      <lines>Glória no porvir!<br/>Glória eterna no porvir!<br/>Há, sim, sombras neste vale,<br/>mas há glória no porvir.</lines>
    </verse>
    <verse name="v2">
      <lines break="optional">Temos sombras neste vale,<br/>mas fragrância ao derredor;<br/>pois, as rosas da montanha<br/>nos transmitem seu olor.</lines>
      <lines>O bom Mestre nos anima<br/>na subida a prosseguir:<br/>Há, sim, sombras neste vale,<br/>mas há glória no porvir.</lines>
    </verse>
    <verse name="v3">
      <lines break="optional">Mas as sombras deste vale,<br/>de uma vez se desfarão,<br/>com a vinda mui gloriosa<br/>do Senhor da criação.</lines>
      <lines>Eia, pois, ó vós remidos,<br/>escutai-O a repetir:<br/>Há, sim, sombras neste vale,<br/>mas há glória no porvir.</lines>
    </verse>
  </lyrics>
</song>
