<?xml version='1.0' encoding='UTF-8'?>
<song xmlns="http://openlyrics.info/namespace/2009/song" version="0.8" createdIn="OpenLP 2.0.1" modifiedIn="OpenLP 2.0.1" modifiedDate="2013-11-14T21:42:54">
  <properties>
    <titles>
      <title>CC 338 Redentor</title>
      <title>Wilmot</title>
    </titles>
    <verseOrder>v1 v2 v3 v4</verseOrder>
    <authors>
      <author>Antônio Neves</author>
      <author>Carl Weber</author>
    </authors>
    <songbooks>
      <songbook name="Cantor Cristão" entry="338"/>
    </songbooks>
  </properties>
  <lyrics>
    <verse name="v1">
      <lines break="optional">Sei que vive o Redentor,<br/>sei que há vida em seu favor,</lines>
      <lines>que, se aqui na cruz morreu,<br/>reina em glória lá no céu.</lines>
    </verse>
    <verse name="v2">
      <lines break="optional">Vive para interceder<br/>e nas lutas me valer;</lines>
      <lines>vive pra me sustentar,<br/>e do mal me resguardar.</lines>
    </verse>
    <verse name="v3">
      <lines break="optional">Deus me livra de temor,<br/>minorando a minha dor,</lines>
      <lines>a tristeza me desfaz,<br/>dá-me gozo, vida e paz.</lines>
    </verse>
    <verse name="v4">
      <lines break="optional">Vive! hosanas eu Lhe dou!<br/>Vive! reina! e salvo eu sou!</lines>
      <lines>Vivo nele, o Redentor,<br/>sempre firme em seu amor!</lines>
    </verse>
  </lyrics>
</song>
