{
    "livro": "Oséias",
    "capitulo": 14,
    "titulos": {
        "1": "Chamado para voltar ao Senhor",
        "9": "Apelo final"
    },
    "versiculos": {
        "1": "“Israel, volte para o Senhor ,",
        "2": "Tragam palavras",
        "3": "A Assíria não nos salvará.",
        "4": "“Vou curar a rebeldia deles.",
        "5": "Serei para Israel como orvalho;",
        "6": "Os seus ramos se estenderão,",
        "7": "Os que se assentavam",
        "8": "“Ó Efraim, que tenho eu",
        "9": "Quem é sábio,"
    }
}